setup.py
lmdb/__init__.py
lmdb/lmdb.py
lmdb/web.py
python_lmdb.egg-info/PKG-INFO
python_lmdb.egg-info/SOURCES.txt
python_lmdb.egg-info/dependency_links.txt
python_lmdb.egg-info/top_level.txt