Metadata-Version: 1.1
Name: python-lmdb
Version: 1.0.0b1
Summary: simple lmdb bindings written using ctypes
Home-page: http://github.com/fritz0705/python-lmdb.git
Author: Fritz Grimpen
Author-email: fritz@grimpen.net
License: http://opensource.org/licenses/MIT
Platform: UNKNOWN
Classifier: Development Status :: 4 - Beta
Classifier: Operating System :: POSIX
Classifier: Programming Language :: Python :: 3.3
Classifier: Topic :: Database :: Database Engines/Servers
